<?xml version="1.0" encoding="utf-8" standalone="yes"?>
<edmx:Edmx Version="1.0" xmlns:edmx="http://schemas.microsoft.com/ado/2007/06/edmx">
	<edmx:DataServices m:DataServiceVersion="2.0" xmlns:m="http://schemas.microsoft.com/ado/2007/08/dataservices/metadata">
		<Schema Namespace="default" xmlns:d="http://schemas.microsoft.com/ado/2007/08/dataservices"
			xmlns:m="http://schemas.microsoft.com/ado/2007/08/dataservices/metadata" xmlns="http://schemas.microsoft.com/ado/2008/09/edm">
			<EntityType Name="employeesType">
				<Key>
					<PropertyRef Name="EmployeeID"/>
				</Key>
				<Property Name="EmployeeID" Type="Edm.Int32" Nullable="false"/>
				<Property Name="Age" Type="Edm.Int32"/>
				<Property Name="Attrition" Type="Edm.String" MaxLength="50"/>
				<Property Name="BusinessTravel" Type="Edm.String" MaxLength="50"/>
				<Property Name="Department" Type="Edm.String" MaxLength="50"/>
				<Property Name="DistanceFromHome" Type="Edm.Int32"/>
				<Property Name="Education" Type="Edm.String" MaxLength="50"/>
				<Property Name="EducationField" Type="Edm.String" MaxLength="50"/>
				<Property Name="EmployeeCount" Type="Edm.Int32"/>
				<Property Name="Gender" Type="Edm.String" MaxLength="50"/>
				<Property Name="JobLevel" Type="Edm.Int32"/>
				<Property Name="JobRole" Type="Edm.String" MaxLength="50"/>
				<Property Name="MaritalStatus" Type="Edm.String" MaxLength="50"/>
				<Property Name="MonthlyIncome" Type="Edm.Int32"/>
				<Property Name="NumCompaniesWorked" Type="Edm.Int32"/>
				<Property Name="PercentSalaryHike" Type="Edm.Int32"/>
				<Property Name="StandardHours" Type="Edm.Int32"/>
				<Property Name="StockOptionLevel" Type="Edm.Int32"/>
				<Property Name="TotalWorkingYears" Type="Edm.Int32"/>
				<Property Name="TrainingTimesLastYear" Type="Edm.Int32"/>
				<Property Name="YearsAtCompany" Type="Edm.Int32"/>
				<Property Name="YearsSinceLastPromotion" Type="Edm.Int32"/>
				<Property Name="YearsWithCurrManager" Type="Edm.Int32"/>
				<Property Name="EnvironmentSatisfaction" Type="Edm.Int32"/>
				<Property Name="JobSatisfaction" Type="Edm.Int32"/>
				<Property Name="WorkLifeBalance" Type="Edm.Int32"/>
				<Property Name="JobInvolvement" Type="Edm.Int32"/>
				<Property Name="PerformanceRating" Type="Edm.Int32"/>
			</EntityType>
			<EntityContainer Name="v2" m:IsDefaultEntityContainer="true">
				<EntitySet Name="employees" EntityType="default.employeesType"/>
			</EntityContainer>
		</Schema>
	</edmx:DataServices>
</edmx:Edmx>